{
    "toPlay": [
        {
            "name": "Hellblade: Senua's Sacrifice",
            "status": "not_began",
            "playtime": 8
        },
        {
            "name": "Resident Evil 4",
            "status": "not_began",
            "playtime": 24,
            "includes_dlc": true
        },
        {
            "name": "Judgement",
            "status": "not_began",
            "playtime": 30
        },
        {
            "name": "Lost Judgement",
            "status": "not_began",
            "playtime": 40,
            "includes_dlc": true
        },
        {
            "name": "Life is Strange: True Colors",
            "status": "not_began",
            "playtime": 16,
            "includes_dlc": true
        },
        {
            "name": "Witcher 3",
            "status": "not_began",
            "playtime": 100,
            "includes_dlc": true
        }
    ],
    "toRevisit": [
        {
            "name": "Dead by Daylight",
            "status": "not_began",
            "playtime": 9999
        },
        {
            "name": "FF15",
            "status": "not_began",
            "playtime": 35
        }
    ],
    "wantToPlay": [
        {
            "name": "Like a Dragon Gaiden: Kiryu",
            "status": "wanna_play"
        },
        {
            "name": "Like a Dragon: Ishin!",
            "status": "wanna_play"
        },
        {
            "name": "Alan Wake 2",
            "status": "wanna_play"
        },
        {
            "name": "Robocop: Rogue City",
            "status": "wanna_play"
        }
    ]
}